mitmwzl/__init__.py
mitmwzl/_constants.py
mitmwzl/_jswzl.py
mitmwzl/_utils.py
mitmwzl-0.2.0.dist-info/METADATA
mitmwzl-0.2.0.dist-info/WHEEL
mitmwzl-0.2.0.dist-info/licenses/LICENSE
mitmwzl-0.2.0.dist-info/RECORD
