Metadata-Version: 2.1
Name: mitmwzl
Version: 0.2.0
Summary: A mitmproxy addon for jswzl
Project-URL: Homepage, https://github.com/AlbertSPedersen/mitmwzl
Project-URL: Issues, https://github.com/AlbertSPedersen/mitmwzl/issues
Author-email: Albert Pedersen <mitmwzl@albertpedersen.com>
License-File: LICENSE
Classifier: License :: OSI Approved :: GNU General Public License v3 (GPLv3)
Classifier: Operating System :: OS Independent
Classifier: Programming Language :: Python :: 3
Requires-Python: >=3.8
Requires-Dist: mitmproxy>=10
